clasaua/__init__.py
clasaua/fonts/open-sans/Apache License.txt
clasaua/fonts/open-sans/OpenSans-Bold.ttf
clasaua/fonts/open-sans/OpenSans-BoldItalic.ttf
clasaua/fonts/open-sans/OpenSans-Italic.ttf
clasaua/fonts/open-sans/OpenSans-Regular.ttf
clasaua/images/logo_foot.png
clasaua/images/logo_left.png
clasaua/images/logo_right.png
clasaua/launcher.py
clasaua/lib/__init__.py
clasaua/lib/clasaua.py
clasaua/lib/clubs.py
clasaua/lib/files.py
clasaua/lib/report_base.py
clasaua/locale/messages_gl.mo
clasaua-0.4.11.dist-info/LICENSE.txt
clasaua-0.4.11.dist-info/LICENSE_GPL3.txt
clasaua-0.4.11.dist-info/LICENSE_GPL3_GL.txt
clasaua-0.4.11.dist-info/METADATA
clasaua-0.4.11.dist-info/WHEEL
clasaua-0.4.11.dist-info/entry_points.txt
clasaua-0.4.11.dist-info/RECORD
