Metadata-Version: 2.1
Name: clasaua
Version: 0.4.11
Summary: Clasificacions circuito galego augas abertas
Home-page: https://github.com/damufo/clasaua/
License: GPLv3
Author: Dani MF
Author-email: dani@damufo.eu
Requires-Python: >=3.8.0,<3.13
Classifier: License :: Other/Proprietary License
Classifier: Programming Language :: Python :: 3
Classifier: Programming Language :: Python :: 3.8
Classifier: Programming Language :: Python :: 3.9
Classifier: Programming Language :: Python :: 3.10
Classifier: Programming Language :: Python :: 3.11
Classifier: Programming Language :: Python :: 3.12
Requires-Dist: odfpy (>=1.4.1,<2.0.0)
Requires-Dist: reportlab (>=4.2.0,<5.0.0)
Project-URL: Repository, https://github.com/damufo/clasaua/
